[
  {
    "Pseudo": "Admin1",
    "MotDePasse": "Abcde!1",
    "Nom": "Biron",
    "Prenom": "Louis-charles",
    "Role": 1
  },
  {
    "Pseudo": "pseudoDefaut1",
    "MotDePasse": "!Soleil01",
    "Nom": "Felix",
    "Prenom": "Blanchette",
    "Role": 0
  },
  {
    "Pseudo": "CRAZY3",
    "MotDePasse": "!Soleil01",
    "Nom": "test",
    "Prenom": "test",
    "Role": 0
  },
  {
    "Pseudo": "Admin1",
    "MotDePasse": "!Soleil01",
    "Nom": "Test",
    "Prenom": "Admin",
    "Role": 1
  },
  {
    "Pseudo": "QDacier9",
    "MotDePasse": "!Soleil01",
    "Nom": "lorman",
    "Prenom": "maek",
    "Role": 0
  }
]